NSFopen/__init__.py
NSFopen/_version.py
NSFopen/example/Calculate_Roughness/Calculate_Roughness.html
NSFopen/example/Calculate_Roughness/Calculate_Roughness.ipynb
NSFopen/example/Calculate_Roughness/Calculate_Roughness.py
NSFopen/example/Calculate_Roughness/sapphire.nid
NSFopen/example/Calculate_Roughness/__pycache__/Calculate_Roughness.cpython-310.pyc
NSFopen/example/Force_Spectroscopy/Force_Spectroscopy.html
NSFopen/example/Force_Spectroscopy/Force_Spectroscopy.ipynb
NSFopen/example/Force_Spectroscopy/Force_Spectroscopy.py
NSFopen/example/Force_Spectroscopy/spectroscopy.nid
NSFopen/example/Lateral_Force/Lateral Force Processing.html
NSFopen/example/Lateral_Force/Lateral Force Processing.ipynb
NSFopen/example/Lateral_Force/Lateral Force Processing.py
NSFopen/example/Lateral_Force/SBS-PMMA.nid
NSFopen/example/Plane_Removal/Plane_Removal.html
NSFopen/example/Plane_Removal/Plane_Removal.ipynb
NSFopen/example/Plane_Removal/Plane_Removal.py
NSFopen/example/Plane_Removal/circles.nid
NSFopen/example/Plane_Removal/circles_holes.nid
NSFopen/example/Plane_Removal/grid.nid
NSFopen/example/Plane_Removal/squares_holes.nid
NSFopen/example/Plotting_Data/MoS2.nid
NSFopen/example/Plotting_Data/Plotting Data.html
NSFopen/example/Plotting_Data/Plotting Data.ipynb
NSFopen/example/Plotting_Data/Plotting Data.py
NSFopen/example/Sharpen_Image/Sharpen Image.html
NSFopen/example/Sharpen_Image/Sharpen Image.ipynb
NSFopen/example/Sharpen_Image/Sharpen Image.py
NSFopen/example/Sharpen_Image/grid.nid
NSFopen/example/Sharpen_Image/img.jpg
NSFopen/example/Spring_Constant/Spring_Constant.html
NSFopen/example/Spring_Constant/Spring_Constant.ipynb
NSFopen/example/Spring_Constant/Spring_Constant.py
NSFopen/example/Spring_Constant/sader.py
NSFopen/example/Spring_Constant/thermal.nid
NSFopen/example/Spring_Constant/thermal.png
NSFopen/example/Spring_Constant/__pycache__/Spring_Constant.cpython-310.pyc
NSFopen/example/Spring_Constant/__pycache__/__init__.cpython-310.pyc
NSFopen/process/__init__.py
NSFopen-2.2.4.dist-info/LICENSE
NSFopen-2.2.4.dist-info/METADATA
NSFopen-2.2.4.dist-info/WHEEL
NSFopen-2.2.4.dist-info/entry_points.txt
NSFopen-2.2.4.dist-info/top_level.txt
NSFopen-2.2.4.dist-info/RECORD
