Metadata-Version: 2.1
Name: NSFopen
Version: 2.2.4
Summary: Python module to open Nanosurf NID and NHF files
Author: Nanosurf AG
Author-email: scripting@nanosurf.com
License: MIT
Classifier: Programming Language :: Python :: 3
Classifier: License :: OSI Approved :: MIT License
Classifier: Operating System :: Microsoft :: Windows
Requires-Python: >=3.9
License-File: LICENSE
Requires-Dist: matplotlib
Requires-Dist: numpy
Requires-Dist: scipy
Requires-Dist: pandas
Requires-Dist: h5py
